brightness_controller_linux/__init__.py
brightness_controller_linux/brightness-reset
brightness_controller_linux/icons/__init__.py
brightness_controller_linux/icons/brightness-controller.svg
brightness_controller_linux/init.py
brightness_controller_linux/setup.py
brightness_controller_linux/ui/License.ui
brightness_controller_linux/ui/__init__.py
brightness_controller_linux/ui/about.py
brightness_controller_linux/ui/about.ui
brightness_controller_linux/ui/help.py
brightness_controller_linux/ui/help.ui
brightness_controller_linux/ui/license.py
brightness_controller_linux/ui/mainwindow.py
brightness_controller_linux/ui/mainwindow.ui
brightness_controller_linux/util/QtSingleApplication.py
brightness_controller_linux/util/__init__.py
brightness_controller_linux/util/check_displays.py
brightness_controller_linux/util/debian_install
brightness_controller_linux/util/executor.py
brightness_controller_linux/util/filepath_handler.py
brightness_controller_linux/util/read_config.py
brightness_controller_linux/util/resource_provider.py
brightness_controller_linux/util/write_config.py
brightness_controller_linux-2.4.dist-info/entry_points.txt
brightness_controller_linux-2.4.dist-info/WHEEL
brightness_controller_linux-2.4.dist-info/METADATA
brightness_controller_linux-2.4.dist-info/RECORD
